raster_pro
vector_pro
